pynetsuite/__init__.py
pynetsuite/api_client.py
pynetsuite/api_response.py
pynetsuite/configuration.py
pynetsuite/exceptions.py
pynetsuite/py.typed
pynetsuite/rest.py
pynetsuite/api/__init__.py
pynetsuite/api/account_api.py
pynetsuite/api/credit_memo_api.py
pynetsuite/api/currency_api.py
pynetsuite/api/customer_api.py
pynetsuite/api/invoice_api.py
pynetsuite/api/sales_tax_item_api.py
pynetsuite/api/tax_type_api.py
pynetsuite/api/term_api.py
pynetsuite/api/vendor_api.py
pynetsuite/api/vendor_bill_api.py
pynetsuite/models/__init__.py
pynetsuite/models/account.py
pynetsuite/models/account_account_context_search_collection.py
pynetsuite/models/account_account_context_search_element.py
pynetsuite/models/account_acct_type.py
pynetsuite/models/account_collection.py
pynetsuite/models/account_general_rate.py
pynetsuite/models/account_localizations_collection.py
pynetsuite/models/account_localizations_element.py
pynetsuite/models/account_s_spec_acct.py
pynetsuite/models/credit_memo.py
pynetsuite/models/credit_memo_accounting_book_detail_collection.py
pynetsuite/models/credit_memo_accounting_book_detail_element.py
pynetsuite/models/credit_memo_apply_collection.py
pynetsuite/models/credit_memo_apply_element.py
pynetsuite/models/credit_memo_billing_address.py
pynetsuite/models/credit_memo_collection.py
pynetsuite/models/credit_memo_custom_form.py
pynetsuite/models/credit_memo_item_collection.py
pynetsuite/models/credit_memo_item_element.py
pynetsuite/models/credit_memo_item_element_cost_estimate_type.py
pynetsuite/models/credit_memo_item_element_vsoe_permit_discount.py
pynetsuite/models/credit_memo_item_element_vsoe_sop_group.py
pynetsuite/models/credit_memo_item_inventory_detail.py
pynetsuite/models/credit_memo_item_inventory_detail_inventory_assignment_collection.py
pynetsuite/models/credit_memo_item_inventory_detail_inventory_assignment_element.py
pynetsuite/models/credit_memo_shipping_address.py
pynetsuite/models/credit_memo_source.py
pynetsuite/models/credit_memo_status.py
pynetsuite-1.3.0.dist-info/METADATA
pynetsuite-1.3.0.dist-info/WHEEL
pynetsuite-1.3.0.dist-info/top_level.txt
pynetsuite-1.3.0.dist-info/RECORD
