Metadata-Version: 2.4
Name: pynetsuite
Version: 1.3.0
Summary: NetSuite REST Record API
Home-page: 
Author: Oracle NetSuite
Author-email: Oracle NetSuite <info@netsuite.com>
License: UNLICENSED
Project-URL: Repository, https://github.com/GIT_USER_ID/GIT_REPO_ID
Keywords: OpenAPI,OpenAPI-Generator,NetSuite REST Record API
Requires-Python: >=3.9
Requires-Dist: urllib3<3.0.0,>=2.1.0
Requires-Dist: python-dateutil>=2.8.2
Requires-Dist: pydantic>=2
Requires-Dist: typing-extensions>=4.7.1
Dynamic: author
